{
  "method": "get_daily_avg_network_difficulty",
  "module": "pro",
  "kwargs": {
    "start_date": "2019-02-01",
    "end_date": "2019-02-28",
    "sort": "asc"
  },
  "log_timestamp": "2020-10-28-11:55:17",
  "res": [
    {
      "UTCDate": "2019-02-01",
      "unixTimeStamp": "1548979200",
      "networkDifficulty": "2,408.028"
    },
    {
      "UTCDate": "2019-02-02",
      "unixTimeStamp": "1549065600",
      "networkDifficulty": "2,358.910"
    },
    {
      "UTCDate": "2019-02-03",
      "unixTimeStamp": "1549152000",
      "networkDifficulty": "2,354.610"
    },
    {
      "UTCDate": "2019-02-04",
      "unixTimeStamp": "1549238400",
      "networkDifficulty": "2,361.903"
    },
    {
      "UTCDate": "2019-02-05",
      "unixTimeStamp": "1549324800",
      "networkDifficulty": "2,363.999"
    },
    {
      "UTCDate": "2019-02-06",
      "unixTimeStamp": "1549411200",
      "networkDifficulty": "2,348.840"
    },
    {
      "UTCDate": "2019-02-07",
      "unixTimeStamp": "1549497600",
      "networkDifficulty": "2,334.071"
    },
    {
      "UTCDate": "2019-02-08",
      "unixTimeStamp": "1549584000",
      "networkDifficulty": "2,371.717"
    },
    {
      "UTCDate": "2019-02-09",
      "unixTimeStamp": "1549670400",
      "networkDifficulty": "2,370.090"
    },
    {
      "UTCDate": "2019-02-10",
      "unixTimeStamp": "1549756800",
      "networkDifficulty": "2,799.616"
    },
    {
      "UTCDate": "2019-02-11",
      "unixTimeStamp": "1549843200",
      "networkDifficulty": "2,790.454"
    },
    {
      "UTCDate": "2019-02-12",
      "unixTimeStamp": "1549929600",
      "networkDifficulty": "2,845.497"
    },
    {
      "UTCDate": "2019-02-13",
      "unixTimeStamp": "1550016000",
      "networkDifficulty": "2,813.683"
    },
    {
      "UTCDate": "2019-02-14",
      "unixTimeStamp": "1550102400",
      "networkDifficulty": "2,763.886"
    },
    {
      "UTCDate": "2019-02-15",
      "unixTimeStamp": "1550188800",
      "networkDifficulty": "2,758.556"
    },
    {
      "UTCDate": "2019-02-16",
      "unixTimeStamp": "1550275200",
      "networkDifficulty": "2,791.493"
    },
    {
      "UTCDate": "2019-02-17",
      "unixTimeStamp": "1550361600",
      "networkDifficulty": "2,787.184"
    },
    {
      "UTCDate": "2019-02-18",
      "unixTimeStamp": "1550448000",
      "networkDifficulty": "2,800.544"
    },
    {
      "UTCDate": "2019-02-19",
      "unixTimeStamp": "1550534400",
      "networkDifficulty": "2,931.316"
    },
    {
      "UTCDate": "2019-02-20",
      "unixTimeStamp": "1550620800",
      "networkDifficulty": "2,934.330"
    },
    {
      "UTCDate": "2019-02-21",
      "unixTimeStamp": "1550707200",
      "networkDifficulty": "2,935.973"
    },
    {
      "UTCDate": "2019-02-22",
      "unixTimeStamp": "1550793600",
      "networkDifficulty": "2,909.985"
    },
    {
      "UTCDate": "2019-02-23",
      "unixTimeStamp": "1550880000",
      "networkDifficulty": "3,019.639"
    },
    {
      "UTCDate": "2019-02-24",
      "unixTimeStamp": "1550966400",
      "networkDifficulty": "3,010.990"
    },
    {
      "UTCDate": "2019-02-25",
      "unixTimeStamp": "1551052800",
      "networkDifficulty": "2,966.100"
    },
    {
      "UTCDate": "2019-02-26",
      "unixTimeStamp": "1551139200",
      "networkDifficulty": "2,978.234"
    },
    {
      "UTCDate": "2019-02-27",
      "unixTimeStamp": "1551225600",
      "networkDifficulty": "2,974.809"
    },
    {
      "UTCDate": "2019-02-28",
      "unixTimeStamp": "1551312000",
      "networkDifficulty": "2,927.453"
    }
  ]
}